README.md
setup.py
aspect_based_sentiment_analysis/__init__.py
aspect_based_sentiment_analysis/alignment.py
aspect_based_sentiment_analysis/aux_models.py
aspect_based_sentiment_analysis/data_types.py
aspect_based_sentiment_analysis/loads.py
aspect_based_sentiment_analysis/models.py
aspect_based_sentiment_analysis/pipelines.py
aspect_based_sentiment_analysis/plots.py
aspect_based_sentiment_analysis/professors.py
aspect_based_sentiment_analysis/text_splitters.py
aspect_based_sentiment_analysis/utils.py
aspect_based_sentiment_analysis/training/__init__.py
aspect_based_sentiment_analysis/training/callbacks.py
aspect_based_sentiment_analysis/training/classifier.py
aspect_based_sentiment_analysis/training/data_types.py
aspect_based_sentiment_analysis/training/datasets.py
aspect_based_sentiment_analysis/training/errors.py
aspect_based_sentiment_analysis/training/metrics.py
aspect_based_sentiment_analysis/training/routines.py
aspect_based_sentiment_analysis_g.egg-info/PKG-INFO
aspect_based_sentiment_analysis_g.egg-info/SOURCES.txt
aspect_based_sentiment_analysis_g.egg-info/dependency_links.txt
aspect_based_sentiment_analysis_g.egg-info/requires.txt
aspect_based_sentiment_analysis_g.egg-info/top_level.txt