Metadata-Version: 2.1
Name: aspect-based-sentiment-analysis-g
Version: 1.0.0
Summary: Aspect Based Sentiment Analysis: Transformer & Interpretability (TensorFlow)
Home-page: https://github.com/ozkanonur/Aspect-Based-Sentiment-Analysis
Author:  Rafal Rolczynski
Author-email: rafal.rolczynski@gmail.com
License: Apache-2.0
Platform: UNKNOWN
Requires-Python: >=3.7.*
